dbks/__init__.py
dbks/cli.py
dbks/client.py
dbks/response_handler.py
dbks/runtime.py
dbks/util.py
dbks/cli_command/__init__.py
dbks/cli_command/cluster.py
dbks/cli_command/permission.py
dbks/cli_command/workspace.py
dbks/cluster/__init__.py
dbks/cluster/api.py
dbks/cluster/controller.py
dbks/library/__init__.py
dbks/library/api.py
dbks/permission/__init__.py
dbks/permission/api.py
dbks/permission/controller.py
dbks/workspace/__init__.py
dbks/workspace/api.py
dbks/workspace/controller.py
dbks-0.0.1.dist-info/LICENSE
dbks-0.0.1.dist-info/METADATA
dbks-0.0.1.dist-info/WHEEL
dbks-0.0.1.dist-info/entry_points.txt
dbks-0.0.1.dist-info/top_level.txt
dbks-0.0.1.dist-info/RECORD
