Metadata-Version: 2.1
Name: dbks
Version: 0.0.1
Summary: Databricks API client
Home-page: https://github.com/vincentlam/dbks
Author: Vincent Lam
Author-email: vincent@lam.is
License: UNKNOWN
Platform: UNKNOWN
Classifier: Programming Language :: Python :: 3
Classifier: License :: OSI Approved :: MIT License
Classifier: Operating System :: OS Independent
Requires-Python: >=3.6
Requires-Dist: click
Requires-Dist: pyyaml
Requires-Dist: requests
